Metadata-Version: 1.1
Name: magwitch
Version: 0.1.0
Summary: Decorator for your functions, for easy tune of boolean arguments
Home-page: https://github.com/aluriak/magwitch
Author: Lucas Bourneuf
Author-email: lucas.bourneuf@laposte.net
License: MIT
Keywords: decorator,bool,arguments,helper
Platform: UNKNOWN
Classifier: Development Status :: 5 - Production/Stable
Classifier: Intended Audience :: Developers
Classifier: Programming Language :: Python :: 3
Classifier: Programming Language :: Python :: 3.4
